{"path":".obsidian/plugins/text-extractor/cache/2./040profane-世俗-论文-【小绿鲸】超棒的英文文献阅读器（附安装包+总结笔记+思维导图）-2.小绿鲸8大主要功能简介.png-b384d7e2611a48ff2b87f4ade924a4c8.json","text":"仑 6 大 翻 译 引 擎 : 实 现 多 翻 译 引 擎 自 由 切 换 ; 、 学 科 翻 译 : 可 无 限 添 加 本 专 业 术 语 库 , 自 0 翻 译 @ 定 X 翻 译 结 果 ; G 全 文 翻 译 : 一 键 翻 译 PDF 文 献 , 保 留 原 文 格 式 , 还 支 持 下 载 Word 版 。 @ 一 篓 文 献 对 应 一 篓 笔 记 , 笔 记 形 式 多 样 ; @ 大 纲 、 导 图 自 由 切 换 , 帮 助 梳 理 文 献 思 路 ; 、 7 种 科 研 场 景 下 的 笔 记 模 板 , 直 接 套 用 更 方 @ 笔 i c @ PDF 上 内 容 和 图 片 一 键 导 入 笔 记 中 , 笔 记 和 PDF 可 实 现 双 向 定 位 。 迂'〉 可 以 与 Zotero 联 用 @ 速 凄 白 一 键 提 取 图 表 , 让 你 快 速 掌 握 文 献 重 点 ; 俐 侦 白 一 键 提 取 参 考 文 献 , 进 行 文 献 追 溯 。 咤 @ 多 条 语 料 在 线 改 写 , 引 用 句 子 文 献 溯 源 ; 小 绿 鲸 @ 写 作 吊 社 团 @ 可 边 阅 读 边 整 理 写 作 素 材 , 即 使 散 落 在 不 同 文 献 中 的 内 容 也 能 有 效 管 理 。 @ 自 动 识 别 文 献 题 录 信 息 , 无 限 级 新 建 文 件 夹 管 理 ; G 文 献 管 理 白 可 做 备 注 、 打 标 签 、 标 记 重 要 度 ; 皂 标 签 筛 选 搭 配 智 能 搜 索 , 精 准 锁 定 文 献 。 @ 云 端 存 储 , 可 无 上 限 扩 容 ; 云 端 阅 读 O 云 端 阅 读 一〔Q 支 持 Mac/Windows/Web/H5 版 本 互 通 阅 读 。 @ 超 全 批 注 功 能 : 高 亮 、 下 划 线 、 自 由 划 D pDF 阅 浩 技 注 「〔 线 、 添 加 注 释 、 插 入 形 状 或 图 片 等 ; ] 佑 块 ) @ 多 种 阅 读 模 式 : 对 比 阅 读 、 全 屏 阅 读 、 护 眼 模 式 。 @ e 累 G 宇 一 水 二 乙 大 江 1 @ 网 站 上 的 PDF 文 献 可 一 键 导 入 小 绿 鲸","libVersion":"0.0.0","langs":"chi_sim+eng","hash":"","size":0}